pxscraper/__init__.py
pxscraper-0.0.0.dist-info/METADATA
pxscraper-0.0.0.dist-info/WHEEL
pxscraper-0.0.0.dist-info/top_level.txt
pxscraper-0.0.0.dist-info/RECORD
